ipwhois/__init__.py
ipwhois/asn.py
ipwhois/exceptions.py
ipwhois/experimental.py
ipwhois/hr.py
ipwhois/ipwhois.py
ipwhois/net.py
ipwhois/nir.py
ipwhois/rdap.py
ipwhois/utils.py
ipwhois/whois.py
ipwhois/scripts/ipwhois_cli.py
ipwhois/scripts/ipwhois_utils_cli.py
ipwhois/scripts/py36.py
ipwhois/scripts/test.py
ipwhois/scripts/urllib3.py
ipwhois-1.3.0.dist-info/LICENSE.txt
ipwhois-1.3.0.dist-info/METADATA
ipwhois-1.3.0.dist-info/WHEEL
ipwhois-1.3.0.dist-info/entry_points.txt
ipwhois-1.3.0.dist-info/top_level.txt
ipwhois-1.3.0.dist-info/RECORD
