Metadata-Version: 2.1
Name: ipwhois
Version: 1.3.0
Summary: Retrieve and parse whois data for IPv4 and IPv6 addresses.
Home-page: https://github.com/secynic/ipwhois
Download-URL: https://github.com/secynic/ipwhois/tarball/master
Author: Philip Hane
Author-email: secynic@gmail.com
License: BSD
Keywords: Python, WHOIS, RWhois, Referral Whois, ASN, IP Address, IP, IPv4, IPv6,,IETF, REST, Arin, Ripe, Apnic, Lacnic, Afrinic, NIC, National Information,Center, RDAP, RIR, Regional Internet Registry, NIR, National Internet,Registry, ASN origin, Origin
Classifier: Development Status :: 5 - Production/Stable
Classifier: Intended Audience :: Developers
Classifier: Intended Audience :: Information Technology
Classifier: Intended Audience :: Science/Research
Classifier: License :: OSI Approved :: BSD License
Classifier: Operating System :: OS Independent
Classifier: Programming Language :: Python
Classifier: Programming Language :: Python :: 2
Classifier: Programming Language :: Python :: 2.7
Classifier: Programming Language :: Python :: 3
Classifier: Programming Language :: Python :: 3.4
Classifier: Programming Language :: Python :: 3.5
Classifier: Programming Language :: Python :: 3.6
Classifier: Programming Language :: Python :: 3.7
Classifier: Programming Language :: Python :: 3.8
Classifier: Programming Language :: Python :: 3.9
Classifier: Programming Language :: Python :: 3.10
Classifier: Programming Language :: Python :: 3.11
Classifier: Programming Language :: Python :: 3.12
Classifier: Topic :: Internet
Classifier: Topic :: Software Development
License-File: LICENSE.txt
Requires-Dist: dnspython
Requires-Dist: ipaddr==2.2.0; python_version < "3.3"
Requires-Dist: defusedxml
